{"css_animations.md":"rtDYZmgN","css_backgroundenhancement.md":"BG5w5HnC","css_borderradius.md":"DkaOCJLZ","css_boxmodel.md":"B-wgFSC3","css_boxshadow.md":"BOnnkj9u","css_colors.md":"O3qHVv1c","css_documentflow.md":"vXuq9edo","css_flexiblebox.md":"LBGLEbF6","css_float.md":"DBeGIXjm","css_gradients.md":"CrTnnH9H","css_grid.md":"qoTQUihZ","css_inheritance.md":"C16fFH5j","css_mediaqueries.md":"BGwOjklt","css_multicolumn.md":"XyTwH8QL","css_position.md":"VBAeca7b","css_selectors.md":"CqFHHGOD","css_tablelayout.md":"7ym10bJY","css_texteffects.md":"BDVZ33-b","css_transform.md":"B-3ee1bn","css_transitions.md":"QV0CdfJs","css_units.md":"DuR8r3Rc","datastructuresandalgorithms_algorithmcomplexity.md":"CuZOv6qI","datastructuresandalgorithms_array.md":"BbqgxXdD","datastructuresandalgorithms_backtrackingalgorithms.md":"Dd7CmLIe","datastructuresandalgorithms_bfs.md":"DfqLq7qa","datastructuresandalgorithms_dfs.md":"rqYFU1-3","datastructuresandalgorithms_dynamicprogramming.md":"x3xL6Sdd","datastructuresandalgorithms_graph.md":"Bp4vKlr_","datastructuresandalgorithms_greedyalgorithms.md":"D2vHcfd5","datastructuresandalgorithms_hashtable.md":"BS8iRWtk","datastructuresandalgorithms_heap.md":"229uPpAY","datastructuresandalgorithms_linkedlist.md":"CcbaUYyE","datastructuresandalgorithms_map.md":"BiMF3Vhy","datastructuresandalgorithms_queue.md":"svAcOBCA","datastructuresandalgorithms_recursionalgorithms.md":"nBg_5ttI","datastructuresandalgorithms_searchalgorithms.md":"CQeRPUml","datastructuresandalgorithms_set.md":"BU8xWHcl","datastructuresandalgorithms_slidewindow.md":"B2QnMmnW","datastructuresandalgorithms_sortalgorithms.md":"DVYSH-lN","datastructuresandalgorithms_stack.md":"5q1wmiNw","datastructuresandalgorithms_tree.md":"DQbOOsCe","datastructuresandalgorithms_twopointers.md":"BkOfJ6m-","designpatterns_adapterpattern.md":"BC2Duc-p","designpatterns_chainofresponsibilitypattern.md":"Dpo9ohiI","designpatterns_commandpattern.md":"E4xdZ3Xp","designpatterns_compositepattern.md":"vDhKputS","designpatterns_constructorpattern.md":"CcWejinV","designpatterns_decoratorpattern.md":"Hl0B_jxz","designpatterns_facadepattern.md":"CGZXyOXx","designpatterns_factorypattern.md":"CLnpdXYV","designpatterns_flyweightpattern.md":"dy7gECCn","designpatterns_iteratorpattern.md":"DRD6RX4X","designpatterns_mediatorpattern.md":"B5zW4PIi","designpatterns_modulepattern.md":"BqhdidOj","designpatterns_mvc.md":"arzf4HdN","designpatterns_mvvm.md":"wGCeFsYg","designpatterns_observerpattern.md":"BOpPu3OL","designpatterns_patternprinciple.md":"JrGW-gHC","designpatterns_patternsummarize.md":"BBmdHoWB","designpatterns_prototypepattern.md":"S28vyAZn","designpatterns_proxypattern.md":"C49VSLfF","designpatterns_pubsubpattern.md":"KUggeGTP","designpatterns_singletonpattern.md":"Cmz8Rz2G","designpatterns_statepattern.md":"UbroTg53","designpatterns_strategypattern.md":"Cb1k2Iif","designpatterns_templatemethodpattern.md":"DSxbqkex","forntengineering_codecompilers.md":"Bn7HDaMB","forntengineering_engineertools.md":"C10P0g-z","forntengineering_gulp.md":"b--4r1cz","forntengineering_intro.md":"BaZV5A7d","forntengineering_linters.md":"CCBNuccx","forntengineering_monorepo.md":"DpZ07z76","forntengineering_packagemanagers.md":"CpOtfKQa","forntengineering_parcel.md":"BgXVfqaY","forntengineering_rollup.md":"938HjT37","forntengineering_rspack.md":"BnculmHO","forntengineering_testing.md":"BJJwgOhP","forntengineering_tsup.md":"BhdX97nc","forntengineering_vite.md":"CsXjuenn","forntengineering_webpack.md":"v-zSsKBl","frameworks_react_buildtools.md":"C0S8J0ON","frameworks_react_componentandprops.md":"9wrbViji","frameworks_react_componentcommunication.md":"Jkbc_w82","frameworks_react_conditionalrendering.md":"BvAHM3KA","frameworks_react_customhook.md":"D-_V-O8_","frameworks_react_elementrendering.md":"D0wLP3xb","frameworks_react_form.md":"BNyCo1n_","frameworks_react_handlingevents.md":"mj5J2ba4","frameworks_react_hoc.md":"42CH-Hiq","frameworks_react_importandexport.md":"BFgWWnox","frameworks_react_importantinfo.md":"BKsBPf8p","frameworks_react_intro.md":"BX6eLoqI","frameworks_react_jsx.md":"C5P4o535","frameworks_react_listrendering.md":"DB5q51lG","frameworks_react_performanceoptimization.md":"ow5HuVX2","frameworks_react_portals.md":"MsYdkt4s","frameworks_react_react_redux.md":"jbmV736b","frameworks_react_react_router.md":"BW6gXq70","frameworks_react_reacttransitiongroup.md":"C3_T7UtX","frameworks_react_stateandlifecycle.md":"C868T46g","frameworks_react_style.md":"TfmFTI5i","frameworks_react_useactionstate.md":"B8KHlQus","frameworks_react_usecallback.md":"CvKN4bdE","frameworks_react_usecontext.md":"Bwc6u2BP","frameworks_react_usedebugvalue.md":"CWLi7HoV","frameworks_react_usedeferredvalue.md":"BXuJ2z7n","frameworks_react_useeffect.md":"B1KSoIVH","frameworks_react_useeffectevent.md":"Cp2gH31i","frameworks_react_useformstatus.md":"CSE7yLNi","frameworks_react_useid.md":"Dyn-KSOD","frameworks_react_useimperativehandle.md":"BzZAgO8x","frameworks_react_useinsertioneffect.md":"CvvjG_I0","frameworks_react_uselayouteffect.md":"VlNXYPlo","frameworks_react_usememo.md":"BFxaRIeM","frameworks_react_useoptimistic.md":"CpEkzzXI","frameworks_react_usereducer.md":"ChkVbfk-","frameworks_react_useref.md":"Cp87x0Eu","frameworks_react_usestate.md":"Cjzjy49W","frameworks_react_usesyncexternalstore.md":"CtjYb6K_","frameworks_react_usetransition.md":"e3_nh63x","frameworks_vue_asynccomponents.md":"DHu9yhQ4","frameworks_vue_buildtools.md":"Dvq-pZIV","frameworks_vue_button.md":"DIJAcqJ3","frameworks_vue_codegen.md":"DT-IiZAD","frameworks_vue_collapse.md":"CFkGCi_t","frameworks_vue_compileandrun.md":"wSQm6nrs","frameworks_vue_compiler.md":"CrArx0mM","frameworks_vue_compilerinfo.md":"cm1eC2rj","frameworks_vue_componentcommunication.md":"D7ASFaQ7","frameworks_vue_componentessence.md":"D8EW9MP-","frameworks_vue_composablests.md":"D9qaf-Gj","frameworks_vue_computed.md":"DNrUp-_i","frameworks_vue_computedandwatch.md":"Cek3pl0F","frameworks_vue_createrenderer.md":"b6PSRwQP","frameworks_vue_customdirectives.md":"DYoarRsP","frameworks_vue_customhooks.md":"wSvw65GU","frameworks_vue_customref.md":"Ct7b-DuX","frameworks_vue_declarativeui.md":"wjPLuf38","frameworks_vue_defineasynccomponent.md":"CFQyDWR9","frameworks_vue_dropdown.md":"B1LIT4wc","frameworks_vue_form.md":"CwQ5Ek55","frameworks_vue_imperativeanddeclarative.md":"BaAZ4dpJ","frameworks_vue_input.md":"BGIwa0QP","frameworks_vue_intro.md":"yUFwj3vB","frameworks_vue_isomorphicrendering.md":"DBfOxYdw","frameworks_vue_keepalive.md":"CZ4mc48Y","frameworks_vue_keepalivecomponent.md":"CMMnh645","frameworks_vue_lifecyclehooks.md":"UanOcVn4","frameworks_vue_message.md":"CzGKzFQh","frameworks_vue_nexttick.md":"Bua2qMbc","frameworks_vue_nodeops.md":"CGVgPkIq","frameworks_vue_parser.md":"BemlB950","frameworks_vue_patchkeyedchildren.md":"Dmgw3E5R","frameworks_vue_pinia.md":"DS1rnB6s","frameworks_vue_plugins.md":"CoIY54Ui","frameworks_vue_processcommentnode.md":"CjZFodPC","frameworks_vue_processcomponent.md":"8erMPmPz","frameworks_vue_processelement.md":"C_x6VPOA","frameworks_vue_processfragment.md":"KWTNSrqD","frameworks_vue_processtext.md":"BK6nnDNA","frameworks_vue_progress.md":"DtMgkRx9","frameworks_vue_provideandinject.md":"Dc7upAnC","frameworks_vue_quickstart.md":"D0cw0LKh","frameworks_vue_reactive.md":"BZzTvEML","frameworks_vue_reactivityfundamentals.md":"DjTCst1s","frameworks_vue_reactivityupdate.md":"C8KV1reF","frameworks_vue_ref.md":"CLQ02DdO","frameworks_vue_renderer.md":"BOqc9cOD","frameworks_vue_scheduler.md":"BqMtnuqc","frameworks_vue_select.md":"-vPKBhYq","frameworks_vue_slideeffect.md":"crmsaABZ","frameworks_vue_suspense.md":"CL6XoVtg","frameworks_vue_switch.md":"TEX3TfHh","frameworks_vue_teleport.md":"Bo5PASdP","frameworks_vue_teleportcomponent.md":"BPEre0B_","frameworks_vue_templaterefs.md":"CamvBnJl","frameworks_vue_templatesyntax.md":"DSor-W2Q","frameworks_vue_tooltip.md":"CjjP_chx","frameworks_vue_transform.md":"BWFZT0Pj","frameworks_vue_transition.md":"CmqM8Yv4","frameworks_vue_transitioncomponent.md":"7sFMkRIa","frameworks_vue_transitiongroup.md":"B-HnM6YZ","frameworks_vue_treeshaking.md":"CQSS3F0u","frameworks_vue_typescriptsupport.md":"BzleDE8T","frameworks_vue_vdom.md":"tFOeEq1c","frameworks_vue_vnode.md":"BeMMF-6D","frameworks_vue_vuecatalog.md":"Cb74Ueum","frameworks_vue_vuerouter.md":"Ck0JZIns","frameworks_vue_watch.md":"B--jhVuK","frameworks_vue_watcheffect.md":"XOZOqtdJ","git_git.md":"Dn_emWtZ","html_ajax.md":"4ghJNn_e","html_asyncscript.md":"B-wQ6uuj","html_canvasandsvg.md":"CDevgh7b","html_commontags.md":"1Dv1IJr7","html_dataattributes.md":"BKmkQeKJ","html_domattributes.md":"BwUuCo8p","html_domevents.md":"CYVOUupT","html_draganddrop.md":"-YXjrnE6","html_enhancedforms.md":"HNicaZAl","html_geolocation.md":"FisSWY3-","html_history.md":"8E8b2QPo","html_html5newfeatures.md":"BPl9cXgr","html_htmlbasicstructure.md":"Dk2XXGOP","html_multimediaelements.md":"DHozOdFG","html_semantichtml.md":"DRS3YSb2","html_websockets.md":"CvrVu_Cv","html_webstorage.md":"Rs1WkL1k","html_webworkers.md":"gIxhSJlI","index.md":"CLQUqXF8","intro.md":"DSAl8Qax","js_array.md":"BkWEe9sA","js_arraybuffer.md":"BmftVw6g","js_arrayhandlewriting.md":"D58hSEYg","js_async.md":"DsSjGQy0","js_axioshandlewriting.md":"o8LbqVyD","js_basicfunction.md":"Mv59wDYL","js_basicprimitivetype.md":"BOJYNcO2","js_classbasic.md":"CdBAxjAe","js_classextends.md":"APZMQUfz","js_closure.md":"DJH6Fb59","js_collectionprimitivetypes.md":"CT3RW9bU","js_comparemodule.md":"DdCEmTl3","js_copy.md":"CYFLz4Eh","js_crossorigin.md":"CN6yPiWS","js_decorator.md":"Dhtv27k5","js_designpattern.md":"D7oC6L6n","js_eighttypes.md":"Dkhg9-Vz","js_equal.md":"DQHjGWKl","js_errorhandling.md":"DWBdbGmS","js_eventloop.md":"IR9TK-8A","js_executioncontextandstack.md":"DXRHUCGR","js_function.md":"DR0d3rl3","js_functionhandlewriting.md":"C3ed_ykT","js_generator.md":"C2REn4Ed","js_generatorapply.md":"9CXcf4Lu","js_globalmethods.md":"2Oet8tiD","js_highlevelfunction.md":"CtJtvdk3","js_inherit.md":"hpy02Kyq","js_iterator.md":"Bi3eaS5V","js_jsonserialize.md":"FI_lbUvv","js_lexicalscope.md":"DPaNiCX2","js_memoryspace.md":"B6hY7iMW","js_module.md":"D7vA-5AQ","js_number.md":"C3QDL_RT","js_object.md":"CDRwvP9k","js_objecthandlewriting.md":"DtNNl-lP","js_operator.md":"gmLEwMNr","js_optimize.md":"CvtPkbtP","js_primitivewrappertypes.md":"DL6-olTq","js_promise.md":"C2GFtZwG","js_promisehandlewriting.md":"BO-TFJra","js_prototype.md":"xyjXOBQz","js_proxy.md":"aVygA5Zy","js_reflect.md":"CvUXdLjZ","js_regexp.md":"uvUbC_HZ","js_setandmap.md":"BA7XjhAd","js_strict.md":"t4j4qJw_","js_string.md":"CUPOZbdP","js_symbol.md":"CCLJ6_6Z","js_this.md":"DOepdp4U","js_variablesdeclare.md":"CVSo0ziO","js_variablesdestructuring.md":"efPVJMk1","networkandbrowsers_browsercache.md":"CSVWmq5h","networkandbrowsers_cdn.md":"D0JtylrI","networkandbrowsers_csrfandxss.md":"fLCLXRrk","networkandbrowsers_dns.md":"Cn84sdYO","networkandbrowsers_headers.md":"14l2JXRm","networkandbrowsers_http.md":"B2IJ42O7","networkandbrowsers_https.md":"6O4N_r7j","networkandbrowsers_ip.md":"D6unCBBG","networkandbrowsers_osi.md":"C9zgDykE","networkandbrowsers_processandthread.md":"D-JItst1","networkandbrowsers_renderingprocess.md":"f2ZCm7gb","networkandbrowsers_tcp.md":"BIoCdrZX","networkandbrowsers_udp.md":"BvurKg4m","regexp_regexp.md":"dpKTbB0k","typescript_typescript.md":"CWVLRJHN"}
